{
  "version": 2,
  "checkpoint_selection": "min_training_loss",
  "best_epoch": 20,
  "best_training_loss": 0.5520245092255729,
  "macro_auc_test_at_best_epoch": 0.4970958209506029,
  "per_digit_auc_at_best_epoch": {
    "0": 0.6068030222652842,
    "1": 0.6870798874824191,
    "2": 0.6258034623073543,
    "3": 0.6298855636355364,
    "4": 0.41256326930625575,
    "5": 0.4574056877194056,
    "6": 0.6207234002222931,
    "7": 0.2438026735041917,
    "8": 0.44266711960455296,
    "9": 0.24422412345873554
  },
  "macro_auc_test_pruned_active_spheres": 0.4995304324231576,
  "per_digit_auc_test_pruned_active_spheres": {
    "0": 0.5661426050939853,
    "1": 0.6188876102800154,
    "2": 0.6561612340672897,
    "3": 0.7584510143793521,
    "4": 0.4057465572594416,
    "5": 0.6224650781402048,
    "6": 0.26442067382944323,
    "7": 0.14350844435317017,
    "8": 0.6686341474838879,
    "9": 0.290886959344785
  },
  "curvature": 1.0,
  "n_spheres": 30,
  "train_normal_digits": [
    0,
    1,
    2,
    3
  ],
  "test_digits": [
    0,
    1,
    2,
    3,
    4,
    5,
    6,
    7,
    8,
    9
  ],
  "objective": "union-soft",
  "unsupervised": true,
  "ae_checkpoint": "samplesvdd/hySpUnsup/runs/my_v3_ae200_stage1/ae_stage1_ep200.pth",
  "prune": {
    "train_argmin_counts": [
      11,
      20,
      66,
      8,
      22,
      702,
      15,
      8,
      18508,
      15,
      197,
      19,
      151,
      6,
      11,
      6,
      71,
      14,
      68,
      3,
      3,
      217,
      2414,
      5,
      388,
      31,
      35,
      57,
      38,
      7
    ],
    "silhouette_mean_per_cluster_euclidean_z": {
      "0": null,
      "1": null,
      "2": null,
      "3": null,
      "4": null,
      "5": null,
      "6": null,
      "7": null,
      "8": null,
      "9": null,
      "10": null,
      "11": null,
      "12": null,
      "13": null,
      "14": null,
      "15": null,
      "16": null,
      "17": null,
      "18": null,
      "19": null,
      "20": null,
      "21": null,
      "22": null,
      "23": null,
      "24": null,
      "25": null,
      "26": null,
      "27": null,
      "28": null,
      "29": null
    },
    "active_cluster_mask": [
      false,
      true,
      true,
      false,
      true,
      true,
      false,
      false,
      true,
      false,
      true,
      false,
      true,
      false,
      false,
      false,
      true,
      false,
      true,
      false,
      false,
      true,
      true,
      false,
      true,
      true,
      true,
      true,
      true,
      false
    ]
  },
  "split_overloaded": {
    "enabled": true,
    "max_cluster_fraction": 0.2,
    "applied": true,
    "n_train": 23116,
    "cap_count": 4624,
    "counts_before": [
      0,
      20,
      69,
      0,
      22,
      702,
      0,
      0,
      18612,
      0,
      199,
      0,
      151,
      0,
      0,
      0,
      71,
      0,
      71,
      0,
      0,
      217,
      2423,
      0,
      398,
      31,
      35,
      57,
      38,
      0
    ],
    "overloaded_clusters": [
      8
    ],
    "spare_inactive_clusters": [
      0,
      3,
      6,
      7,
      9,
      11,
      13,
      14,
      15,
      17,
      19,
      20,
      23,
      29
    ],
    "splits": [
      {
        "source_cluster": 8,
        "source_count": 18612,
        "groups_after_split": [
          4270,
          4077,
          3679,
          3553,
          3033
        ],
        "new_clusters_activated": [
          0,
          3,
          6,
          7
        ]
      }
    ],
    "active_cluster_mask_after_split": [
      true,
      true,
      true,
      true,
      true,
      true,
      true,
      true,
      true,
      false,
      true,
      false,
      true,
      false,
      false,
      false,
      true,
      false,
      true,
      false,
      false,
      true,
      true,
      false,
      true,
      true,
      true,
      true,
      true,
      false
    ]
  },
  "hybrid_rebalance": {
    "enabled": true,
    "lb_min_cluster_members": 20,
    "ub_max_cluster_fraction": 0.2,
    "max_iters": 4,
    "hard_cap_enabled": true,
    "chaos_factor": 0.15,
    "iterations": [
      {
        "iter": 1,
        "lb": {
          "enabled": true,
          "counts": [
            0,
            106,
            1481,
            0,
            96,
            2374,
            0,
            0,
            20,
            66,
            595,
            42,
            418,
            6,
            106,
            135,
            140,
            36,
            231,
            3,
            127,
            425,
            13760,
            8,
            734,
            31,
            1274,
            648,
            213,
            41
          ],
          "active_before": [
            true,
            true,
            true,
            true,
            true,
            true,
            true,
            true,
            true,
            false,
            true,
            false,
            true,
            false,
            false,
            false,
            true,
            false,
            true,
            false,
            false,
            true,
            true,
            false,
            true,
            true,
            true,
            true,
            true,
            false
          ],
          "active_after": [
            false,
            true,
            true,
            false,
            true,
            true,
            false,
            false,
            true,
            true,
            true,
            true,
            true,
            false,
            true,
            true,
            true,
            true,
            true,
            false,
            true,
            true,
            true,
            false,
            true,
            true,
            true,
            true,
            true,
            true
          ],
          "changed": true
        },
        "ub": {
          "enabled": true,
          "max_cluster_fraction": 0.2,
          "applied": true,
          "n_train": 23116,
          "cap_count": 4624,
          "counts_before": [
            0,
            106,
            1481,
            0,
            96,
            2374,
            0,
            0,
            20,
            66,
            596,
            43,
            418,
            0,
            106,
            135,
            141,
            36,
            234,
            0,
            127,
            425,
            13771,
            0,
            734,
            31,
            1274,
            648,
            213,
            41
          ],
          "overloaded_clusters": [
            22
          ],
          "spare_inactive_clusters": [
            0,
            3,
            6,
            7,
            13,
            19,
            23
          ],
          "splits": [
            {
              "source_cluster": 22,
              "source_count": 13771,
              "groups_after_split": [
                6183,
                4164,
                3424
              ],
              "new_clusters_activated": [
                0,
                3
              ]
            }
          ],
          "active_cluster_mask_after_split": [
            true,
            true,
            true,
            true,
            true,
            true,
            false,
            false,
            true,
            true,
            true,
            true,
            true,
            false,
            true,
            true,
            true,
            true,
            true,
            false,
            true,
            true,
            true,
            false,
            true,
            true,
            true,
            true,
            true,
            true
          ]
        },
        "hard_cap": {
          "enabled": true,
          "max_cluster_fraction": 0.2,
          "chaos_factor": 0.15,
          "applied": true,
          "n_train": 23116,
          "cap_count": 4624,
          "counts_before": [
            0,
            425,
            2092,
            0,
            134,
            7900,
            0,
            0,
            511,
            137,
            2519,
            47,
            644,
            0,
            112,
            473,
            241,
            36,
            1341,
            0,
            172,
            870,
            1277,
            0,
            1000,
            160,
            1799,
            953,
            226,
            47
          ],
          "counts_after": [
            0,
            579,
            2162,
            0,
            144,
            4624,
            0,
            0,
            850,
            380,
            2652,
            55,
            651,
            0,
            147,
            507,
            394,
            40,
            1539,
            0,
            302,
            907,
            1674,
            0,
            1191,
            313,
            2269,
            1434,
            253,
            49
          ],
          "overflow_reassigned": 3276
        },
        "changed": true
      },
      {
        "iter": 2,
        "lb": {
          "enabled": true,
          "counts": [
            0,
            750,
            2636,
            0,
            998,
            241,
            0,
            0,
            0,
            0,
            3907,
            439,
            172,
            28,
            552,
            1283,
            0,
            1653,
            7331,
            10,
            0,
            1089,
            171,
            35,
            208,
            0,
            292,
            1,
            545,
            775
          ],
          "active_before": [
            true,
            true,
            true,
            true,
            true,
            true,
            false,
            false,
            true,
            true,
            true,
            true,
            true,
            false,
            true,
            true,
            true,
            true,
            true,
            false,
            true,
            true,
            true,
            false,
            true,
            true,
            true,
            true,
            true,
            true
          ],
          "active_after": [
            false,
            true,
            true,
            false,
            true,
            true,
            false,
            false,
            false,
            false,
            true,
            true,
            true,
            true,
            true,
            true,
            false,
            true,
            true,
            false,
            false,
            true,
            true,
            true,
            true,
            false,
            true,
            false,
            true,
            true
          ],
          "changed": true
        },
        "ub": {
          "enabled": true,
          "max_cluster_fraction": 0.2,
          "applied": true,
          "n_train": 23116,
          "cap_count": 4624,
          "counts_before": [
            0,
            750,
            2636,
            0,
            998,
            241,
            0,
            0,
            0,
            0,
            3907,
            439,
            172,
            28,
            552,
            1283,
            0,
            1653,
            7342,
            0,
            0,
            1089,
            171,
            35,
            208,
            0,
            292,
            0,
            545,
            775
          ],
          "overloaded_clusters": [
            18
          ],
          "spare_inactive_clusters": [
            0,
            3,
            6,
            7,
            8,
            9,
            16,
            19,
            20,
            25,
            27
          ],
          "splits": [
            {
              "source_cluster": 18,
              "source_count": 7342,
              "groups_after_split": [
                4678,
                2664
              ],
              "new_clusters_activated": [
                0
              ]
            }
          ],
          "active_cluster_mask_after_split": [
            true,
            true,
            true,
            false,
            true,
            true,
            false,
            false,
            false,
            false,
            true,
            true,
            true,
            true,
            true,
            true,
            false,
            true,
            true,
            false,
            false,
            true,
            true,
            true,
            true,
            false,
            true,
            false,
            true,
            true
          ]
        },
        "hard_cap": {
          "enabled": true,
          "max_cluster_fraction": 0.2,
          "chaos_factor": 0.15,
          "applied": true,
          "n_train": 23116,
          "cap_count": 4624,
          "counts_before": [
            0,
            1216,
            2941,
            0,
            1760,
            357,
            0,
            0,
            0,
            0,
            5272,
            1118,
            172,
            28,
            601,
            1592,
            0,
            3050,
            452,
            0,
            0,
            1096,
            340,
            45,
            218,
            0,
            421,
            0,
            1642,
            795
          ],
          "counts_after": [
            0,
            1218,
            2941,
            0,
            1772,
            363,
            0,
            0,
            0,
            0,
            4624,
            1256,
            172,
            28,
            601,
            1606,
            0,
            3050,
            465,
            0,
            0,
            1096,
            472,
            60,
            386,
            0,
            566,
            0,
            1645,
            795
          ],
          "overflow_reassigned": 648
        },
        "changed": true
      },
      {
        "iter": 3,
        "lb": {
          "enabled": true,
          "counts": [
            0,
            9,
            342,
            0,
            954,
            4292,
            0,
            0,
            2,
            0,
            72,
            7676,
            2,
            0,
            119,
            2378,
            0,
            234,
            1513,
            37,
            0,
            39,
            523,
            300,
            0,
            0,
            4429,
            40,
            108,
            47
          ],
          "active_before": [
            true,
            true,
            true,
            false,
            true,
            true,
            false,
            false,
            false,
            false,
            true,
            true,
            true,
            true,
            true,
            true,
            false,
            true,
            true,
            false,
            false,
            true,
            true,
            true,
            true,
            false,
            true,
            false,
            true,
            true
          ],
          "active_after": [
            false,
            false,
            true,
            false,
            true,
            true,
            false,
            false,
            false,
            false,
            true,
            true,
            false,
            false,
            true,
            true,
            false,
            true,
            true,
            true,
            false,
            true,
            true,
            true,
            false,
            false,
            true,
            true,
            true,
            true
          ],
          "changed": true
        },
        "ub": {
          "enabled": true,
          "max_cluster_fraction": 0.2,
          "applied": true,
          "n_train": 23116,
          "cap_count": 4624,
          "counts_before": [
            0,
            0,
            342,
            0,
            956,
            4301,
            0,
            0,
            0,
            0,
            72,
            7676,
            0,
            0,
            119,
            2378,
            0,
            234,
            1513,
            37,
            0,
            39,
            523,
            300,
            0,
            0,
            4429,
            42,
            108,
            47
          ],
          "overloaded_clusters": [
            11
          ],
          "spare_inactive_clusters": [
            0,
            1,
            3,
            6,
            7,
            8,
            9,
            12,
            13,
            16,
            20,
            24,
            25
          ],
          "splits": [
            {
              "source_cluster": 11,
              "source_count": 7676,
              "groups_after_split": [
                5199,
                2477
              ],
              "new_clusters_activated": [
                0
              ]
            }
          ],
          "active_cluster_mask_after_split": [
            true,
            false,
            true,
            false,
            true,
            true,
            false,
            false,
            false,
            false,
            true,
            true,
            false,
            false,
            true,
            true,
            false,
            true,
            true,
            true,
            false,
            true,
            true,
            true,
            false,
            false,
            true,
            true,
            true,
            true
          ]
        },
        "hard_cap": {
          "enabled": true,
          "max_cluster_fraction": 0.2,
          "chaos_factor": 0.15,
          "applied": true,
          "n_train": 23116,
          "cap_count": 4624,
          "counts_before": [
            0,
            0,
            352,
            0,
            1827,
            5224,
            0,
            0,
            0,
            0,
            183,
            439,
            0,
            0,
            119,
            2579,
            0,
            235,
            3260,
            41,
            0,
            121,
            1692,
            1410,
            0,
            0,
            5265,
            94,
            228,
            47
          ],
          "counts_after": [
            0,
            0,
            379,
            0,
            1831,
            4624,
            0,
            0,
            0,
            0,
            231,
            481,
            0,
            0,
            133,
            2580,
            0,
            299,
            3260,
            53,
            0,
            121,
            1999,
            1592,
            0,
            0,
            4624,
            576,
            286,
            47
          ],
          "overflow_reassigned": 1241
        },
        "changed": true
      },
      {
        "iter": 4,
        "lb": {
          "enabled": true,
          "counts": [
            0,
            68,
            6170,
            0,
            23,
            79,
            0,
            0,
            0,
            0,
            26,
            5382,
            1,
            0,
            1492,
            26,
            0,
            6,
            59,
            0,
            0,
            1,
            7705,
            1944,
            0,
            0,
            21,
            0,
            113,
            0
          ],
          "active_before": [
            true,
            false,
            true,
            false,
            true,
            true,
            false,
            false,
            false,
            false,
            true,
            true,
            false,
            false,
            true,
            true,
            false,
            true,
            true,
            true,
            false,
            true,
            true,
            true,
            false,
            false,
            true,
            true,
            true,
            true
          ],
          "active_after": [
            false,
            true,
            true,
            false,
            true,
            true,
            false,
            false,
            false,
            false,
            true,
            true,
            false,
            false,
            true,
            true,
            false,
            false,
            true,
            false,
            false,
            false,
            true,
            true,
            false,
            false,
            true,
            false,
            true,
            false
          ],
          "changed": true
        },
        "ub": {
          "enabled": true,
          "max_cluster_fraction": 0.2,
          "applied": true,
          "n_train": 23116,
          "cap_count": 4624,
          "counts_before": [
            0,
            68,
            6172,
            0,
            23,
            79,
            0,
            0,
            0,
            0,
            26,
            5384,
            0,
            0,
            1492,
            26,
            0,
            0,
            59,
            0,
            0,
            0,
            7709,
            1944,
            0,
            0,
            21,
            0,
            113,
            0
          ],
          "overloaded_clusters": [
            2,
            11,
            22
          ],
          "spare_inactive_clusters": [
            0,
            3,
            6,
            7,
            8,
            9,
            12,
            13,
            16,
            17,
            19,
            20,
            21,
            24,
            25,
            27,
            29
          ],
          "splits": [
            {
              "source_cluster": 2,
              "source_count": 6172,
              "groups_after_split": [
                4010,
                2162
              ],
              "new_clusters_activated": [
                0
              ]
            },
            {
              "source_cluster": 11,
              "source_count": 5384,
              "groups_after_split": [
                2975,
                2409
              ],
              "new_clusters_activated": [
                3
              ]
            },
            {
              "source_cluster": 22,
              "source_count": 7709,
              "groups_after_split": [
                4063,
                3646
              ],
              "new_clusters_activated": [
                6
              ]
            }
          ],
          "active_cluster_mask_after_split": [
            true,
            true,
            true,
            true,
            true,
            true,
            true,
            false,
            false,
            false,
            true,
            true,
            false,
            false,
            true,
            true,
            false,
            false,
            true,
            false,
            false,
            false,
            true,
            true,
            false,
            false,
            true,
            false,
            true,
            false
          ]
        },
        "hard_cap": {
          "enabled": true,
          "max_cluster_fraction": 0.2,
          "chaos_factor": 0.15,
          "applied": true,
          "n_train": 23116,
          "cap_count": 4624,
          "counts_before": [
            0,
            168,
            57,
            0,
            36,
            137,
            0,
            0,
            0,
            0,
            646,
            9,
            0,
            0,
            3597,
            64,
            0,
            0,
            82,
            0,
            0,
            0,
            325,
            14403,
            0,
            0,
            86,
            0,
            3506,
            0
          ],
          "counts_after": [
            0,
            803,
            383,
            0,
            135,
            825,
            0,
            0,
            0,
            0,
            4194,
            157,
            0,
            0,
            4146,
            147,
            0,
            0,
            637,
            0,
            0,
            0,
            1395,
            4624,
            0,
            0,
            1046,
            0,
            4624,
            0
          ],
          "overflow_reassigned": 9779
        },
        "changed": true
      }
    ],
    "applied": true,
    "active_cluster_mask_after_hybrid": [
      true,
      true,
      true,
      true,
      true,
      true,
      true,
      false,
      false,
      false,
      true,
      true,
      false,
      false,
      true,
      true,
      false,
      false,
      true,
      false,
      false,
      false,
      true,
      true,
      false,
      false,
      true,
      false,
      true,
      false
    ]
  },
  "union_test_metrics_active_spheres": {
    "union_frac_inside": 0.0,
    "union_margin_mean": 16.824419021606445,
    "union_margin_std": 7.123000144958496
  }
}