{
  "n_samples": 2000,
  "per_cluster": {
    "0": {
      "n": 0,
      "class_counts": {
        "0": 0,
        "1": 0,
        "2": 0,
        "3": 0,
        "4": 0,
        "5": 0,
        "6": 0,
        "7": 0,
        "8": 0,
        "9": 0
      },
      "class_density": {
        "0": 0.0,
        "1": 0.0,
        "2": 0.0,
        "3": 0.0,
        "4": 0.0,
        "5": 0.0,
        "6": 0.0,
        "7": 0.0,
        "8": 0.0,
        "9": 0.0
      },
      "entropy_nat": 0.0
    },
    "1": {
      "n": 9,
      "class_counts": {
        "0": 0,
        "1": 9,
        "2": 0,
        "3": 0,
        "4": 0,
        "5": 0,
        "6": 0,
        "7": 0,
        "8": 0,
        "9": 0
      },
      "class_density": {
        "0": 0.0,
        "1": 1.0,
        "2": 0.0,
        "3": 0.0,
        "4": 0.0,
        "5": 0.0,
        "6": 0.0,
        "7": 0.0,
        "8": 0.0,
        "9": 0.0
      },
      "entropy_nat": -0.0
    },
    "2": {
      "n": 11,
      "class_counts": {
        "0": 6,
        "1": 0,
        "2": 1,
        "3": 1,
        "4": 0,
        "5": 0,
        "6": 0,
        "7": 1,
        "8": 2,
        "9": 0
      },
      "class_density": {
        "0": 0.5454545454545454,
        "1": 0.0,
        "2": 0.09090909090909091,
        "3": 0.09090909090909091,
        "4": 0.0,
        "5": 0.0,
        "6": 0.0,
        "7": 0.09090909090909091,
        "8": 0.18181818181818182,
        "9": 0.0
      },
      "entropy_nat": 1.2945
    },
    "3": {
      "n": 18,
      "class_counts": {
        "0": 0,
        "1": 18,
        "2": 0,
        "3": 0,
        "4": 0,
        "5": 0,
        "6": 0,
        "7": 0,
        "8": 0,
        "9": 0
      },
      "class_density": {
        "0": 0.0,
        "1": 1.0,
        "2": 0.0,
        "3": 0.0,
        "4": 0.0,
        "5": 0.0,
        "6": 0.0,
        "7": 0.0,
        "8": 0.0,
        "9": 0.0
      },
      "entropy_nat": -0.0
    },
    "4": {
      "n": 1626,
      "class_counts": {
        "0": 74,
        "1": 153,
        "2": 188,
        "3": 169,
        "4": 191,
        "5": 180,
        "6": 165,
        "7": 180,
        "8": 151,
        "9": 175
      },
      "class_density": {
        "0": 0.04551045510455105,
        "1": 0.0940959409594096,
        "2": 0.11562115621156212,
        "3": 0.1039360393603936,
        "4": 0.11746617466174662,
        "5": 0.11070110701107011,
        "6": 0.1014760147601476,
        "7": 0.11070110701107011,
        "8": 0.0928659286592866,
        "9": 0.10762607626076261
      },
      "entropy_nat": 2.2794
    },
    "5": {
      "n": 0,
      "class_counts": {
        "0": 0,
        "1": 0,
        "2": 0,
        "3": 0,
        "4": 0,
        "5": 0,
        "6": 0,
        "7": 0,
        "8": 0,
        "9": 0
      },
      "class_density": {
        "0": 0.0,
        "1": 0.0,
        "2": 0.0,
        "3": 0.0,
        "4": 0.0,
        "5": 0.0,
        "6": 0.0,
        "7": 0.0,
        "8": 0.0,
        "9": 0.0
      },
      "entropy_nat": 0.0
    },
    "6": {
      "n": 17,
      "class_counts": {
        "0": 15,
        "1": 0,
        "2": 0,
        "3": 1,
        "4": 0,
        "5": 1,
        "6": 0,
        "7": 0,
        "8": 0,
        "9": 0
      },
      "class_density": {
        "0": 0.8823529411764706,
        "1": 0.0,
        "2": 0.0,
        "3": 0.058823529411764705,
        "4": 0.0,
        "5": 0.058823529411764705,
        "6": 0.0,
        "7": 0.0,
        "8": 0.0,
        "9": 0.0
      },
      "entropy_nat": 0.4438
    },
    "7": {
      "n": 2,
      "class_counts": {
        "0": 2,
        "1": 0,
        "2": 0,
        "3": 0,
        "4": 0,
        "5": 0,
        "6": 0,
        "7": 0,
        "8": 0,
        "9": 0
      },
      "class_density": {
        "0": 1.0,
        "1": 0.0,
        "2": 0.0,
        "3": 0.0,
        "4": 0.0,
        "5": 0.0,
        "6": 0.0,
        "7": 0.0,
        "8": 0.0,
        "9": 0.0
      },
      "entropy_nat": -0.0
    },
    "8": {
      "n": 8,
      "class_counts": {
        "0": 2,
        "1": 0,
        "2": 0,
        "3": 3,
        "4": 0,
        "5": 2,
        "6": 0,
        "7": 0,
        "8": 1,
        "9": 0
      },
      "class_density": {
        "0": 0.25,
        "1": 0.0,
        "2": 0.0,
        "3": 0.375,
        "4": 0.0,
        "5": 0.25,
        "6": 0.0,
        "7": 0.0,
        "8": 0.125,
        "9": 0.0
      },
      "entropy_nat": 1.3209
    },
    "9": {
      "n": 0,
      "class_counts": {
        "0": 0,
        "1": 0,
        "2": 0,
        "3": 0,
        "4": 0,
        "5": 0,
        "6": 0,
        "7": 0,
        "8": 0,
        "9": 0
      },
      "class_density": {
        "0": 0.0,
        "1": 0.0,
        "2": 0.0,
        "3": 0.0,
        "4": 0.0,
        "5": 0.0,
        "6": 0.0,
        "7": 0.0,
        "8": 0.0,
        "9": 0.0
      },
      "entropy_nat": 0.0
    },
    "10": {
      "n": 0,
      "class_counts": {
        "0": 0,
        "1": 0,
        "2": 0,
        "3": 0,
        "4": 0,
        "5": 0,
        "6": 0,
        "7": 0,
        "8": 0,
        "9": 0
      },
      "class_density": {
        "0": 0.0,
        "1": 0.0,
        "2": 0.0,
        "3": 0.0,
        "4": 0.0,
        "5": 0.0,
        "6": 0.0,
        "7": 0.0,
        "8": 0.0,
        "9": 0.0
      },
      "entropy_nat": 0.0
    },
    "11": {
      "n": 3,
      "class_counts": {
        "0": 0,
        "1": 3,
        "2": 0,
        "3": 0,
        "4": 0,
        "5": 0,
        "6": 0,
        "7": 0,
        "8": 0,
        "9": 0
      },
      "class_density": {
        "0": 0.0,
        "1": 1.0,
        "2": 0.0,
        "3": 0.0,
        "4": 0.0,
        "5": 0.0,
        "6": 0.0,
        "7": 0.0,
        "8": 0.0,
        "9": 0.0
      },
      "entropy_nat": -0.0
    },
    "12": {
      "n": 0,
      "class_counts": {
        "0": 0,
        "1": 0,
        "2": 0,
        "3": 0,
        "4": 0,
        "5": 0,
        "6": 0,
        "7": 0,
        "8": 0,
        "9": 0
      },
      "class_density": {
        "0": 0.0,
        "1": 0.0,
        "2": 0.0,
        "3": 0.0,
        "4": 0.0,
        "5": 0.0,
        "6": 0.0,
        "7": 0.0,
        "8": 0.0,
        "9": 0.0
      },
      "entropy_nat": 0.0
    },
    "13": {
      "n": 1,
      "class_counts": {
        "0": 1,
        "1": 0,
        "2": 0,
        "3": 0,
        "4": 0,
        "5": 0,
        "6": 0,
        "7": 0,
        "8": 0,
        "9": 0
      },
      "class_density": {
        "0": 1.0,
        "1": 0.0,
        "2": 0.0,
        "3": 0.0,
        "4": 0.0,
        "5": 0.0,
        "6": 0.0,
        "7": 0.0,
        "8": 0.0,
        "9": 0.0
      },
      "entropy_nat": -0.0
    },
    "14": {
      "n": 5,
      "class_counts": {
        "0": 0,
        "1": 5,
        "2": 0,
        "3": 0,
        "4": 0,
        "5": 0,
        "6": 0,
        "7": 0,
        "8": 0,
        "9": 0
      },
      "class_density": {
        "0": 0.0,
        "1": 1.0,
        "2": 0.0,
        "3": 0.0,
        "4": 0.0,
        "5": 0.0,
        "6": 0.0,
        "7": 0.0,
        "8": 0.0,
        "9": 0.0
      },
      "entropy_nat": -0.0
    },
    "15": {
      "n": 0,
      "class_counts": {
        "0": 0,
        "1": 0,
        "2": 0,
        "3": 0,
        "4": 0,
        "5": 0,
        "6": 0,
        "7": 0,
        "8": 0,
        "9": 0
      },
      "class_density": {
        "0": 0.0,
        "1": 0.0,
        "2": 0.0,
        "3": 0.0,
        "4": 0.0,
        "5": 0.0,
        "6": 0.0,
        "7": 0.0,
        "8": 0.0,
        "9": 0.0
      },
      "entropy_nat": 0.0
    },
    "16": {
      "n": 0,
      "class_counts": {
        "0": 0,
        "1": 0,
        "2": 0,
        "3": 0,
        "4": 0,
        "5": 0,
        "6": 0,
        "7": 0,
        "8": 0,
        "9": 0
      },
      "class_density": {
        "0": 0.0,
        "1": 0.0,
        "2": 0.0,
        "3": 0.0,
        "4": 0.0,
        "5": 0.0,
        "6": 0.0,
        "7": 0.0,
        "8": 0.0,
        "9": 0.0
      },
      "entropy_nat": 0.0
    },
    "17": {
      "n": 0,
      "class_counts": {
        "0": 0,
        "1": 0,
        "2": 0,
        "3": 0,
        "4": 0,
        "5": 0,
        "6": 0,
        "7": 0,
        "8": 0,
        "9": 0
      },
      "class_density": {
        "0": 0.0,
        "1": 0.0,
        "2": 0.0,
        "3": 0.0,
        "4": 0.0,
        "5": 0.0,
        "6": 0.0,
        "7": 0.0,
        "8": 0.0,
        "9": 0.0
      },
      "entropy_nat": 0.0
    },
    "18": {
      "n": 0,
      "class_counts": {
        "0": 0,
        "1": 0,
        "2": 0,
        "3": 0,
        "4": 0,
        "5": 0,
        "6": 0,
        "7": 0,
        "8": 0,
        "9": 0
      },
      "class_density": {
        "0": 0.0,
        "1": 0.0,
        "2": 0.0,
        "3": 0.0,
        "4": 0.0,
        "5": 0.0,
        "6": 0.0,
        "7": 0.0,
        "8": 0.0,
        "9": 0.0
      },
      "entropy_nat": 0.0
    },
    "19": {
      "n": 18,
      "class_counts": {
        "0": 17,
        "1": 0,
        "2": 0,
        "3": 1,
        "4": 0,
        "5": 0,
        "6": 0,
        "7": 0,
        "8": 0,
        "9": 0
      },
      "class_density": {
        "0": 0.9444444444444444,
        "1": 0.0,
        "2": 0.0,
        "3": 0.05555555555555555,
        "4": 0.0,
        "5": 0.0,
        "6": 0.0,
        "7": 0.0,
        "8": 0.0,
        "9": 0.0
      },
      "entropy_nat": 0.2146
    },
    "20": {
      "n": 1,
      "class_counts": {
        "0": 0,
        "1": 1,
        "2": 0,
        "3": 0,
        "4": 0,
        "5": 0,
        "6": 0,
        "7": 0,
        "8": 0,
        "9": 0
      },
      "class_density": {
        "0": 0.0,
        "1": 1.0,
        "2": 0.0,
        "3": 0.0,
        "4": 0.0,
        "5": 0.0,
        "6": 0.0,
        "7": 0.0,
        "8": 0.0,
        "9": 0.0
      },
      "entropy_nat": -0.0
    },
    "21": {
      "n": 28,
      "class_counts": {
        "0": 0,
        "1": 25,
        "2": 0,
        "3": 0,
        "4": 0,
        "5": 0,
        "6": 0,
        "7": 3,
        "8": 0,
        "9": 0
      },
      "class_density": {
        "0": 0.0,
        "1": 0.8928571428571429,
        "2": 0.0,
        "3": 0.0,
        "4": 0.0,
        "5": 0.0,
        "6": 0.0,
        "7": 0.10714285714285714,
        "8": 0.0,
        "9": 0.0
      },
      "entropy_nat": 0.3405
    },
    "22": {
      "n": 7,
      "class_counts": {
        "0": 7,
        "1": 0,
        "2": 0,
        "3": 0,
        "4": 0,
        "5": 0,
        "6": 0,
        "7": 0,
        "8": 0,
        "9": 0
      },
      "class_density": {
        "0": 1.0,
        "1": 0.0,
        "2": 0.0,
        "3": 0.0,
        "4": 0.0,
        "5": 0.0,
        "6": 0.0,
        "7": 0.0,
        "8": 0.0,
        "9": 0.0
      },
      "entropy_nat": -0.0
    },
    "23": {
      "n": 238,
      "class_counts": {
        "0": 70,
        "1": 5,
        "2": 21,
        "3": 27,
        "4": 0,
        "5": 19,
        "6": 49,
        "7": 34,
        "8": 13,
        "9": 0
      },
      "class_density": {
        "0": 0.29411764705882354,
        "1": 0.02100840336134454,
        "2": 0.08823529411764706,
        "3": 0.1134453781512605,
        "4": 0.0,
        "5": 0.07983193277310924,
        "6": 0.20588235294117646,
        "7": 0.14285714285714285,
        "8": 0.0546218487394958,
        "9": 0.0
      },
      "entropy_nat": 1.8662
    },
    "24": {
      "n": 2,
      "class_counts": {
        "0": 0,
        "1": 2,
        "2": 0,
        "3": 0,
        "4": 0,
        "5": 0,
        "6": 0,
        "7": 0,
        "8": 0,
        "9": 0
      },
      "class_density": {
        "0": 0.0,
        "1": 1.0,
        "2": 0.0,
        "3": 0.0,
        "4": 0.0,
        "5": 0.0,
        "6": 0.0,
        "7": 0.0,
        "8": 0.0,
        "9": 0.0
      },
      "entropy_nat": -0.0
    },
    "25": {
      "n": 0,
      "class_counts": {
        "0": 0,
        "1": 0,
        "2": 0,
        "3": 0,
        "4": 0,
        "5": 0,
        "6": 0,
        "7": 0,
        "8": 0,
        "9": 0
      },
      "class_density": {
        "0": 0.0,
        "1": 0.0,
        "2": 0.0,
        "3": 0.0,
        "4": 0.0,
        "5": 0.0,
        "6": 0.0,
        "7": 0.0,
        "8": 0.0,
        "9": 0.0
      },
      "entropy_nat": 0.0
    },
    "26": {
      "n": 0,
      "class_counts": {
        "0": 0,
        "1": 0,
        "2": 0,
        "3": 0,
        "4": 0,
        "5": 0,
        "6": 0,
        "7": 0,
        "8": 0,
        "9": 0
      },
      "class_density": {
        "0": 0.0,
        "1": 0.0,
        "2": 0.0,
        "3": 0.0,
        "4": 0.0,
        "5": 0.0,
        "6": 0.0,
        "7": 0.0,
        "8": 0.0,
        "9": 0.0
      },
      "entropy_nat": 0.0
    },
    "27": {
      "n": 1,
      "class_counts": {
        "0": 1,
        "1": 0,
        "2": 0,
        "3": 0,
        "4": 0,
        "5": 0,
        "6": 0,
        "7": 0,
        "8": 0,
        "9": 0
      },
      "class_density": {
        "0": 1.0,
        "1": 0.0,
        "2": 0.0,
        "3": 0.0,
        "4": 0.0,
        "5": 0.0,
        "6": 0.0,
        "7": 0.0,
        "8": 0.0,
        "9": 0.0
      },
      "entropy_nat": -0.0
    },
    "28": {
      "n": 0,
      "class_counts": {
        "0": 0,
        "1": 0,
        "2": 0,
        "3": 0,
        "4": 0,
        "5": 0,
        "6": 0,
        "7": 0,
        "8": 0,
        "9": 0
      },
      "class_density": {
        "0": 0.0,
        "1": 0.0,
        "2": 0.0,
        "3": 0.0,
        "4": 0.0,
        "5": 0.0,
        "6": 0.0,
        "7": 0.0,
        "8": 0.0,
        "9": 0.0
      },
      "entropy_nat": 0.0
    },
    "29": {
      "n": 5,
      "class_counts": {
        "0": 4,
        "1": 0,
        "2": 0,
        "3": 0,
        "4": 0,
        "5": 0,
        "6": 0,
        "7": 0,
        "8": 1,
        "9": 0
      },
      "class_density": {
        "0": 0.8,
        "1": 0.0,
        "2": 0.0,
        "3": 0.0,
        "4": 0.0,
        "5": 0.0,
        "6": 0.0,
        "7": 0.0,
        "8": 0.2,
        "9": 0.0
      },
      "entropy_nat": 0.5004
    }
  },
  "pruning": {
    "active_cluster_mask": [
      true,
      true,
      true,
      true,
      true,
      true,
      true,
      true,
      true,
      false,
      false,
      true,
      false,
      true,
      true,
      false,
      false,
      false,
      false,
      true,
      true,
      true,
      true,
      true,
      true,
      false,
      true,
      true,
      true,
      true
    ],
    "pruned_cluster_ids": [
      9,
      10,
      12,
      15,
      16,
      17,
      18,
      25
    ],
    "n_active_spheres": 22,
    "nearest_sphere_assignment": "active_argmin",
    "note": "per_cluster uses nearest active sphere (pruned heads excluded from argmin). Hull/legend grey-out uses active_cluster_mask."
  },
  "assignment_diagnostics": {
    "dominant_cluster": 4,
    "dominant_cluster_fraction": 0.813,
    "collapse_detected_ge_0p9": false
  }
}